{
    "job_id": "wzk4h",
    "user_requirements": "a chubby lady with big dark nipple, a short young man , in a libray",
    "character_design": {
        "male": {
            "age": "Young",
            "nationality": "American",
            "height": "Short",
            "body_shape": "Slim",
            "personality": "Shy",
            "penis": "small penis"
        },
        "female": {
            "age": "Adult",
            "nationality": "European",
            "height": "Medium",
            "body_shape": "Chubby",
            "hair_style": "Wavy hair",
            "personality": "Gentle",
            "nipples": "big dark nipple"
        }
    },
    "location_design": {
        "locations": [
            {
                "location": "Main Reading Hall",
                "location_major_elements": [
                    "High arched windows",
                    "Rows of oak desks",
                    "Leather armchairs",
                    "Large carpeted floor"
                ],
                "time": "Afternoon",
                "lying_surfaces": [
                    {
                        "lying_surface": "Oak desk",
                        "objects_on_it": [
                            "Stack of hardcover books",
                            "Open laptop",
                            "Ceramic coffee mug"
                        ]
                    }
                ],
                "sitting_surface": [
                    "Leather armchair",
                    "Office chair"
                ],
                "virtical_surface": [
                    "Floor-to-ceiling bookshelves",
                    "Wooden pillars"
                ],
                "lighting": "Bright natural sunlight streaming through tall windows",
                "female_character": {
                    "top": "Cream cable-knit sweater",
                    "bottom": "Beige plaid midi skirt",
                    "shoes": "Brown leather loafers",
                    "legs": "Bare legs",
                    "bra": "Nude lace bra",
                    "panties": "Beige cotton panties",
                    "accessories": {
                        "face": "Gold-rimmed reading glasses"
                    }
                },
                "male_character": {
                    "top": "Light blue oxford shirt",
                    "bottom": "Navy chinos",
                    "shoes": "Brown leather oxfords",
                    "legs": "Bare legs",
                    "accessories": {
                        "wrist": "Leather strap watch",
                        "face": "Round glasses"
                    }
                },
                "prompts": [
                    "hug, eye_level, Short American young man, Light blue oxford shirt, 1man, wavy, Gold-rimmed reading glasses, Cream cable-knit sweater, Nude lace bra, cleavage, European adult woman, Main Reading Hall, High arched windows, Rows of oak desks, Leather armchairs, Large carpeted floor, Afternoon, Bright natural sunlight streaming through tall windows, lean_against_Wooden pillars, lie_on_Oak desk, Stack of hardcover books, Open laptop, Ceramic coffee mug, sit_on_Leather armchair",
                    "hug, eye_level, Short American young man, Light blue oxford shirt, 1man, wavy, Gold-rimmed reading glasses, Cream cable-knit sweater, Nude lace bra, cleavage, European adult woman, Main Reading Hall, High arched windows, Rows of oak desks, Leather armchairs, Large carpeted floor, Afternoon, Bright natural sunlight streaming through tall windows, lean_against_Floor-to-ceiling bookshelves, lie_on_Oak desk, Stack of hardcover books, Open laptop, Ceramic coffee mug, sit_on_Office chair",
                    "oral, overhead, pov, small penis, 1man, big dark nipple, Gold-rimmed reading glasses, Cream cable-knit sweater, Nude lace bra, cleavage, European adult woman, Main Reading Hall, High arched windows, Rows of oak desks, Leather armchairs, Large carpeted floor, Afternoon, Bright natural sunlight streaming through tall windows"
                ]
            },
            {
                "location": "Rare Books Archives",
                "location_major_elements": [
                    "Dusty leather armchairs",
                    "Floor-to-ceiling bookshelves",
                    "Brass reading lamps",
                    "Old wooden tables"
                ],
                "time": "Night",
                "lying_surfaces": [
                    {
                        "lying_surface": "Old wooden table",
                        "objects_on_it": [
                            "Vintage map",
                            "Magnifying glass",
                            "Leather-bound journal"
                        ]
                    }
                ],
                "sitting_surface": [
                    "Velvet armchair",
                    "Stool"
                ],
                "virtical_surface": [
                    "Iron bookshelves",
                    "Brass lamp stand"
                ],
                "lighting": "Dim, warm yellow light from desk lamps",
                "female_character": {
                    "top": "Burgundy turtleneck",
                    "bottom": "Black leather-look trousers",
                    "shoes": "Black ankle boots",
                    "legs": "Sheer black tights",
                    "bra": "Black lace bra",
                    "panties": "Black lace panties",
                    "accessories": {
                        "wrist": "Silver bangle"
                    }
                },
                "male_character": {
                    "top": "Dark grey hoodie",
                    "bottom": "Dark blue jeans",
                    "shoes": "Black sneakers",
                    "legs": "Bare legs",
                    "accessories": {
                        "hair": "Beanie cap"
                    }
                },
                "prompts": [
                    "kiss, eye_level, Short American young man, Dark grey hoodie, 1man, wavy, Burgundy turtleneck, Black lace bra, cleavage, Silver bangle, European adult woman, Rare Books Archives, Dusty leather armchairs, Floor-to-ceiling bookshelves, Brass reading lamps, Old wooden tables, Night, Dim, warm yellow light from desk lamps, lean_against_Brass lamp stand, lie_on_Old wooden table, Vintage map, Magnifying glass, Leather-bound journal, sit_on_Velvet armchair",
                    "oral, overhead, pov, small penis, 1man, big dark nipple, Burgundy turtleneck, Black lace bra, cleavage, Silver bangle, European adult woman, Rare Books Archives, Dusty leather armchairs, Floor-to-ceiling bookshelves, Brass reading lamps, Old wooden tables, Night, Dim, warm yellow light from desk lamps",
                    "kneeling_doggy, eye_level, side_view, Short American young man, Dark grey hoodie, Dark blue jeans, small penis, 1man, ass, Black leather-look trousers, big dark nipple, nipples slip, wavy, Burgundy turtleneck, Black lace bra, cleavage, woman's back, Burgundy turtleneck, Sheer black tights, Black ankle boots, Silver bangle, European adult woman, Rare Books Archives, Dusty leather armchairs, Floor-to-ceiling bookshelves, Brass reading lamps, Old wooden tables, Night, Dim, warm yellow light from desk lamps"
                ]
            },
            {
                "location": "Rooftop Garden",
                "location_major_elements": [
                    "Stone benches",
                    "Stone fountain",
                    "Rose bushes",
                    "Stone pillars"
                ],
                "time": "Dusk",
                "lying_surfaces": [
                    {
                        "lying_surface": "Stone bench",
                        "objects_on_it": [
                            "Hardcover novel",
                            "Sunglasses"
                        ]
                    }
                ],
                "sitting_surface": [
                    "Stone bench",
                    "Stone steps"
                ],
                "virtical_surface": [
                    "Stone pillars",
                    "Stone fountain"
                ],
                "lighting": "Soft twilight with fading sunlight",
                "female_character": {
                    "top": "White chiffon blouse",
                    "bottom": "Navy blue wrap skirt",
                    "shoes": "White strappy sandals",
                    "legs": "Bare legs",
                    "bra": "White bra",
                    "panties": "White panties",
                    "accessories": {
                        "hair": "Wide-brimmed straw hat",
                        "ear": "Pearl drop earrings"
                    }
                },
                "male_character": {
                    "top": "White linen shirt",
                    "bottom": "Khaki shorts",
                    "shoes": "White canvas sneakers",
                    "legs": "Bare legs",
                    "accessories": {
                        "finger": "Silver ring"
                    }
                },
                "prompts": [
                    "kneeling_doggy, from_above, back, pov, Short American young man, small penis, 1man, ass, Navy blue wrap skirt, wavy, Wide-brimmed straw hat, Pearl drop earrings, woman's back, White chiffon blouse, Bare legs, European adult woman, Rooftop Garden, Stone benches, Stone fountain, Rose bushes, Stone pillars, Dusk, Soft twilight with fading sunlight",
                    "oral, eye_level, side_view, Short American young man, White linen shirt, Khaki shorts, White canvas sneakers, small penis, 1man, ass, Navy blue wrap skirt, big dark nipple, nipples slip, wavy, Wide-brimmed straw hat, Pearl drop earrings, White chiffon blouse, White bra, cleavage, Bare legs, White strappy sandals, European adult woman, Rooftop Garden, Stone benches, Stone fountain, Rose bushes, Stone pillars, Dusk, Soft twilight with fading sunlight",
                    "kiss, eye_level, Short American young man, White linen shirt, 1man, wavy, Wide-brimmed straw hat, Pearl drop earrings, White chiffon blouse, White bra, cleavage, European adult woman, Rooftop Garden, Stone benches, Stone fountain, Rose bushes, Stone pillars, Dusk, Soft twilight with fading sunlight, lean_against_Stone fountain, lie_on_Stone bench, Hardcover novel, Sunglasses, sit_on_Stone steps"
                ]
            }
        ]
    }
}